adafruit_sen6x.py
adafruit_circuitpython_sen6x-1.0.3.dist-info/licenses/LICENSE
adafruit_circuitpython_sen6x-1.0.3.dist-info/METADATA
adafruit_circuitpython_sen6x-1.0.3.dist-info/WHEEL
adafruit_circuitpython_sen6x-1.0.3.dist-info/top_level.txt
adafruit_circuitpython_sen6x-1.0.3.dist-info/RECORD
