Metadata-Version: 2.4
Name: adafruit-circuitpython-sen6x
Version: 1.0.3
Summary: CircuitPython driver for the Sensirion SEN6x environmental sensor node
Author-email: Adafruit Industries <circuitpython@adafruit.com>
License: MIT
Project-URL: Homepage, https://github.com/adafruit/Adafruit_CircuitPython_SEN6x
Keywords: adafruit,blinka,circuitpython,micropython,sen6x,SEN6x,,Sensirion,,environmental,,temperature,,humidity,,co2,,particulate
Classifier: Intended Audience :: Developers
Classifier: Topic :: Software Development :: Libraries
Classifier: Topic :: Software Development :: Embedded Systems
Classifier: Topic :: System :: Hardware
Classifier: License :: OSI Approved :: MIT License
Classifier: Programming Language :: Python :: 3
License-File: LICENSE
Requires-Dist: Adafruit-Blinka
Requires-Dist: adafruit-circuitpython-busdevice
Provides-Extra: optional
Dynamic: license-file
